LICENSE.txt
MANIFEST.in
README.rst
setup.cfg
setup.py
django_federated_login.egg-info/PKG-INFO
django_federated_login.egg-info/SOURCES.txt
django_federated_login.egg-info/dependency_links.txt
django_federated_login.egg-info/requires.txt
django_federated_login.egg-info/top_level.txt
example/__init__.py
example/manage.py
example/settings.py
example/urls.py
example/utils.py
example/views.py
federated_login/__init__.py
federated_login/admin.py
federated_login/auth_backends.py
federated_login/models.py
federated_login/patch_admin.py
federated_login/patches.py
federated_login/store.py
federated_login/urls.py
federated_login/user_factories.py
federated_login/utils.py
federated_login/views.py
federated_login/migrations/0001_initial.py
federated_login/migrations/__init__.py
tests/__init__.py
tests/models.py
tests/settings.py
tests/tests.py
tests/urls.py