Metadata-Version: 1.1
Name: django-federated-login
Version: 1.0.0
Summary: Provides federated login (SSO) to Django projects
Home-page: http://github.com/Bouke/django-federated-login
Author: Bouke Haarsma
Author-email: bouke@webatoom.nl
License: MIT
Platform: UNKNOWN
Classifier: Development Status :: 5 - Production/Stable
Classifier: Environment :: Web Environment
Classifier: Framework :: Django
Classifier: Intended Audience :: Developers
Classifier: License :: OSI Approved :: MIT License
Classifier: Operating System :: OS Independent
Classifier: Programming Language :: Python
Classifier: Programming Language :: Python :: 2
Classifier: Programming Language :: Python :: 2.6
Classifier: Programming Language :: Python :: 2.7
Classifier: Programming Language :: Python :: 3
Classifier: Programming Language :: Python :: 3.2
Classifier: Programming Language :: Python :: 3.3
Classifier: Topic :: Security
Classifier: Topic :: System :: Systems Administration :: Authentication/Directory
